{ "columns":0,
 "grid":
    {
     "height":1,
     "orientation":"orthogonal",
     "width":1
    },
 "margin":0,
 "name":"asteroid",
 "spacing":0,
 "tilecount":7,
 "tiledversion":"2019.08.14",
 "tileheight":120,
 "tiles":[
        {
         "id":0,
         "image":"basic_asteroid_up.png",
         "imageheight":40,
         "imagewidth":96
        }, 
        {
         "id":1,
         "image":"basic_asteroid_vertical.png",
         "imageheight":120,
         "imagewidth":96
        }, 
        {
         "id":2,
         "image":"basic_asteroid_down.png",
         "imageheight":40,
         "imagewidth":96
        }, 
        {
         "id":3,
         "image":"basic_asteroid_lower_connector.png",
         "imageheight":40,
         "imagewidth":96
        }, 
        {
         "id":4,
         "image":"basic_asteroid_upper_connector.png",
         "imageheight":40,
         "imagewidth":96
        }, 
        {
         "id":5,
         "image":"basic_asteroid_dark.png",
         "imageheight":40,
         "imagewidth":96
        }, 
        {
         "id":6,
         "image":"industrialised_asteroid_up.png",
         "imageheight":40,
         "imagewidth":96
        }],
 "tilewidth":96,
 "type":"tileset",
 "version":1.2
}